.coveragerc
LICENSE
MANIFEST.in
README.rst
requirements.txt
setup.py
yturl.py
tests/__init__.py
tests/_test_utils.py
tests/e2e_tests.py
tests/requirements.txt
tests/unit_tests.py
tests/files/embed_restricted
tests/files/success_input
tests/files/success_output
yturl.egg-info/PKG-INFO
yturl.egg-info/SOURCES.txt
yturl.egg-info/dependency_links.txt
yturl.egg-info/entry_points.txt
yturl.egg-info/requires.txt
yturl.egg-info/top_level.txt