Metadata-Version: 1.1
Name: yturl
Version: 2.0.0
Summary: Gets direct media URLs to YouTube media
Home-page: https://github.com/cdown/yturl
Author: Chris Down
Author-email: chris@chrisdown.name
License: Public Domain
Keywords: youtube media video
Platform: UNKNOWN
Classifier: Development Status :: 5 - Production/Stable
Classifier: License :: Public Domain
Classifier: Programming Language :: Python :: 2
Classifier: Programming Language :: Python :: 3
Classifier: Topic :: Multimedia
Classifier: Topic :: Internet
Classifier: Topic :: Utilities
